{
  "resourceType": "ValueSet",
  "id": "UKCore-HumanLanguage",
  "url": "https://fhir.hl7.org.uk/ValueSet/UKCore-HumanLanguage",
  "identifier": [ {
    "system": "urn:ietf:rfc:3986",
    "value": "urn:oid:2.16.840.1.113883.2.1.3.2.4.17.70"
  } ],
  "version": "2.2.0",
  "name": "UKCoreHumanLanguage",
  "title": "UK Core Human Language",
  "status": "retired",
  "date": "2023-12-12",
  "publisher": "HL7 UK",
  "contact": [ {
    "name": "HL7 UK",
    "telecom": [ {
      "system": "email",
      "value": "ukcore@hl7.org.uk",
      "use": "work",
      "rank": 1
    } ]
  } ],
  "description": "A set of codes that define a language used by a person.",
  "copyright": "Copyright © 2021+ HL7 UK Licensed under the Apache License, Version 2.0 (the \"License\"); you may not use this file except in compliance with the License. You may obtain a copy of the License at  http://www.apache.org/licenses/LICENSE-2.0 Unless required by applicable law or agreed to in writing, software distributed under the License is distributed on an \"AS IS\" BASIS, WITHOUT WARRANTIES OR CONDITIONS OF ANY KIND, either express or implied. See the License for the specific language governing permissions and limitations under the License. HL7® FHIR® standard Copyright © 2011+ HL7 The HL7® FHIR® standard is used under the FHIR license. You may obtain a copy of the FHIR license at  https://www.hl7.org/fhir/license.html.",
  "compose": {
    "include": [ {
      "system": "https://fhir.hl7.org.uk/CodeSystem/UKCore-HumanLanguage"
    } ]
  },
  "expansion": {
    "identifier": "7ed29ed3-c1d9-442e-91c3-8c5eb31ea10e",
    "timestamp": "2021-09-09T14:24:53+00:00",
    "total": 190,
    "offset": 0,
    "parameter": [ {
      "name": "version",
      "valueUri": "https://fhir.hl7.org.uk/CodeSystem/UKCore-HumanLanguage|2.1.0"
    }, {
      "name": "count",
      "valueInteger": 2147483647
    }, {
      "name": "offset",
      "valueInteger": 0
    } ],
    "contains": [ {
      "system": "https://fhir.hl7.org.uk/CodeSystem/UKCore-HumanLanguage",
      "code": "ab",
      "display": "Abkhazian"
    }, {
      "system": "https://fhir.hl7.org.uk/CodeSystem/UKCore-HumanLanguage",
      "code": "aa",
      "display": "Afar"
    }, {
      "system": "https://fhir.hl7.org.uk/CodeSystem/UKCore-HumanLanguage",
      "code": "af",
      "display": "Afrikaans"
    }, {
      "system": "https://fhir.hl7.org.uk/CodeSystem/UKCore-HumanLanguage",
      "code": "ak",
      "display": "Akan"
    }, {
      "system": "https://fhir.hl7.org.uk/CodeSystem/UKCore-HumanLanguage",
      "code": "sq",
      "display": "Albanian"
    }, {
      "system": "https://fhir.hl7.org.uk/CodeSystem/UKCore-HumanLanguage",
      "code": "q2",
      "display": "American Sign Language"
    }, {
      "system": "https://fhir.hl7.org.uk/CodeSystem/UKCore-HumanLanguage",
      "code": "am",
      "display": "Amharic"
    }, {
      "system": "https://fhir.hl7.org.uk/CodeSystem/UKCore-HumanLanguage",
      "code": "ar",
      "display": "Arabic"
    }, {
      "system": "https://fhir.hl7.org.uk/CodeSystem/UKCore-HumanLanguage",
      "code": "an",
      "display": "Aragonese"
    }, {
      "system": "https://fhir.hl7.org.uk/CodeSystem/UKCore-HumanLanguage",
      "code": "hy",
      "display": "Armenian"
    }, {
      "system": "https://fhir.hl7.org.uk/CodeSystem/UKCore-HumanLanguage",
      "code": "as",
      "display": "Assamese"
    }, {
      "system": "https://fhir.hl7.org.uk/CodeSystem/UKCore-HumanLanguage",
      "code": "q3",
      "display": "Australian Sign Language"
    }, {
      "system": "https://fhir.hl7.org.uk/CodeSystem/UKCore-HumanLanguage",
      "code": "av",
      "display": "Avaric"
    }, {
      "system": "https://fhir.hl7.org.uk/CodeSystem/UKCore-HumanLanguage",
      "code": "ae",
      "display": "Avestan"
    }, {
      "system": "https://fhir.hl7.org.uk/CodeSystem/UKCore-HumanLanguage",
      "code": "ay",
      "display": "Aymara"
    }, {
      "system": "https://fhir.hl7.org.uk/CodeSystem/UKCore-HumanLanguage",
      "code": "az",
      "display": "Azerbaijani"
    }, {
      "system": "https://fhir.hl7.org.uk/CodeSystem/UKCore-HumanLanguage",
      "code": "bm",
      "display": "Bambara"
    }, {
      "system": "https://fhir.hl7.org.uk/CodeSystem/UKCore-HumanLanguage",
      "code": "ba",
      "display": "Bashkir"
    }, {
      "system": "https://fhir.hl7.org.uk/CodeSystem/UKCore-HumanLanguage",
      "code": "eu",
      "display": "Basque"
    }, {
      "system": "https://fhir.hl7.org.uk/CodeSystem/UKCore-HumanLanguage",
      "code": "be",
      "display": "Belarusian"
    }, {
      "system": "https://fhir.hl7.org.uk/CodeSystem/UKCore-HumanLanguage",
      "code": "bn",
      "display": "Bengali"
    }, {
      "system": "https://fhir.hl7.org.uk/CodeSystem/UKCore-HumanLanguage",
      "code": "bh",
      "display": "Bihari"
    }, {
      "system": "https://fhir.hl7.org.uk/CodeSystem/UKCore-HumanLanguage",
      "code": "bi",
      "display": "Bislama"
    }, {
      "system": "https://fhir.hl7.org.uk/CodeSystem/UKCore-HumanLanguage",
      "code": "nb",
      "display": "Bokmal, Norwegian; Norwegian Bokmal"
    }, {
      "system": "https://fhir.hl7.org.uk/CodeSystem/UKCore-HumanLanguage",
      "code": "bs",
      "display": "Bosnian"
    }, {
      "system": "https://fhir.hl7.org.uk/CodeSystem/UKCore-HumanLanguage",
      "code": "q1",
      "display": "Braille"
    }, {
      "system": "https://fhir.hl7.org.uk/CodeSystem/UKCore-HumanLanguage",
      "code": "br",
      "display": "Breton"
    }, {
      "system": "https://fhir.hl7.org.uk/CodeSystem/UKCore-HumanLanguage",
      "code": "q4",
      "display": "British Sign Language"
    }, {
      "system": "https://fhir.hl7.org.uk/CodeSystem/UKCore-HumanLanguage",
      "code": "bg",
      "display": "Bulgarian"
    }, {
      "system": "https://fhir.hl7.org.uk/CodeSystem/UKCore-HumanLanguage",
      "code": "my",
      "display": "Burmese"
    }, {
      "system": "https://fhir.hl7.org.uk/CodeSystem/UKCore-HumanLanguage",
      "code": "ca",
      "display": "Catalan; Valencian"
    }, {
      "system": "https://fhir.hl7.org.uk/CodeSystem/UKCore-HumanLanguage",
      "code": "km",
      "display": "Central Khmer"
    }, {
      "system": "https://fhir.hl7.org.uk/CodeSystem/UKCore-HumanLanguage",
      "code": "ch",
      "display": "Chamorro"
    }, {
      "system": "https://fhir.hl7.org.uk/CodeSystem/UKCore-HumanLanguage",
      "code": "ce",
      "display": "Chechen"
    }, {
      "system": "https://fhir.hl7.org.uk/CodeSystem/UKCore-HumanLanguage",
      "code": "ny",
      "display": "Chichewa; Chewa; Nyanja"
    }, {
      "system": "https://fhir.hl7.org.uk/CodeSystem/UKCore-HumanLanguage",
      "code": "zh",
      "display": "Chinese"
    }, {
      "system": "https://fhir.hl7.org.uk/CodeSystem/UKCore-HumanLanguage",
      "code": "cu",
      "display": "Church Slavic; Old Slavonic; Church Slavonic; Old Bulgarian; Old Church Slavonic"
    }, {
      "system": "https://fhir.hl7.org.uk/CodeSystem/UKCore-HumanLanguage",
      "code": "cv",
      "display": "Chuvash"
    }, {
      "system": "https://fhir.hl7.org.uk/CodeSystem/UKCore-HumanLanguage",
      "code": "kw",
      "display": "Cornish"
    }, {
      "system": "https://fhir.hl7.org.uk/CodeSystem/UKCore-HumanLanguage",
      "code": "co",
      "display": "Corsican"
    }, {
      "system": "https://fhir.hl7.org.uk/CodeSystem/UKCore-HumanLanguage",
      "code": "cr",
      "display": "Cree"
    }, {
      "system": "https://fhir.hl7.org.uk/CodeSystem/UKCore-HumanLanguage",
      "code": "hr",
      "display": "Croatian"
    }, {
      "system": "https://fhir.hl7.org.uk/CodeSystem/UKCore-HumanLanguage",
      "code": "cs",
      "display": "Czech"
    }, {
      "system": "https://fhir.hl7.org.uk/CodeSystem/UKCore-HumanLanguage",
      "code": "da",
      "display": "Danish"
    }, {
      "system": "https://fhir.hl7.org.uk/CodeSystem/UKCore-HumanLanguage",
      "code": "dv",
      "display": "Divehi; Dhivehi; Maldivian"
    }, {
      "system": "https://fhir.hl7.org.uk/CodeSystem/UKCore-HumanLanguage",
      "code": "nl",
      "display": "Dutch; Flemish"
    }, {
      "system": "https://fhir.hl7.org.uk/CodeSystem/UKCore-HumanLanguage",
      "code": "dz",
      "display": "Dzongkha"
    }, {
      "system": "https://fhir.hl7.org.uk/CodeSystem/UKCore-HumanLanguage",
      "code": "en",
      "display": "English"
    }, {
      "system": "https://fhir.hl7.org.uk/CodeSystem/UKCore-HumanLanguage",
      "code": "eo",
      "display": "Esperanto"
    }, {
      "system": "https://fhir.hl7.org.uk/CodeSystem/UKCore-HumanLanguage",
      "code": "et",
      "display": "Estonian"
    }, {
      "system": "https://fhir.hl7.org.uk/CodeSystem/UKCore-HumanLanguage",
      "code": "ee",
      "display": "Ewe"
    }, {
      "system": "https://fhir.hl7.org.uk/CodeSystem/UKCore-HumanLanguage",
      "code": "fo",
      "display": "Faroese"
    }, {
      "system": "https://fhir.hl7.org.uk/CodeSystem/UKCore-HumanLanguage",
      "code": "fj",
      "display": "Fijian"
    }, {
      "system": "https://fhir.hl7.org.uk/CodeSystem/UKCore-HumanLanguage",
      "code": "fi",
      "display": "Finnish"
    }, {
      "system": "https://fhir.hl7.org.uk/CodeSystem/UKCore-HumanLanguage",
      "code": "fr",
      "display": "French"
    }, {
      "system": "https://fhir.hl7.org.uk/CodeSystem/UKCore-HumanLanguage",
      "code": "ff",
      "display": "Fulah"
    }, {
      "system": "https://fhir.hl7.org.uk/CodeSystem/UKCore-HumanLanguage",
      "code": "gd",
      "display": "Gaelic; Scottish Gaelic"
    }, {
      "system": "https://fhir.hl7.org.uk/CodeSystem/UKCore-HumanLanguage",
      "code": "gl",
      "display": "Galician"
    }, {
      "system": "https://fhir.hl7.org.uk/CodeSystem/UKCore-HumanLanguage",
      "code": "lg",
      "display": "Ganda"
    }, {
      "system": "https://fhir.hl7.org.uk/CodeSystem/UKCore-HumanLanguage",
      "code": "ka",
      "display": "Georgian"
    }, {
      "system": "https://fhir.hl7.org.uk/CodeSystem/UKCore-HumanLanguage",
      "code": "de",
      "display": "German"
    }, {
      "system": "https://fhir.hl7.org.uk/CodeSystem/UKCore-HumanLanguage",
      "code": "el",
      "display": "Greek, Modern (1453-)"
    }, {
      "system": "https://fhir.hl7.org.uk/CodeSystem/UKCore-HumanLanguage",
      "code": "gn",
      "display": "Guarani"
    }, {
      "system": "https://fhir.hl7.org.uk/CodeSystem/UKCore-HumanLanguage",
      "code": "gu",
      "display": "Gujarati"
    }, {
      "system": "https://fhir.hl7.org.uk/CodeSystem/UKCore-HumanLanguage",
      "code": "ht",
      "display": "Haitian; Haitian Creole"
    }, {
      "system": "https://fhir.hl7.org.uk/CodeSystem/UKCore-HumanLanguage",
      "code": "ha",
      "display": "Hausa"
    }, {
      "system": "https://fhir.hl7.org.uk/CodeSystem/UKCore-HumanLanguage",
      "code": "he",
      "display": "Hebrew"
    }, {
      "system": "https://fhir.hl7.org.uk/CodeSystem/UKCore-HumanLanguage",
      "code": "hz",
      "display": "Herero"
    }, {
      "system": "https://fhir.hl7.org.uk/CodeSystem/UKCore-HumanLanguage",
      "code": "hi",
      "display": "Hindi"
    }, {
      "system": "https://fhir.hl7.org.uk/CodeSystem/UKCore-HumanLanguage",
      "code": "ho",
      "display": "Hiri Motu"
    }, {
      "system": "https://fhir.hl7.org.uk/CodeSystem/UKCore-HumanLanguage",
      "code": "hu",
      "display": "Hungarian"
    }, {
      "system": "https://fhir.hl7.org.uk/CodeSystem/UKCore-HumanLanguage",
      "code": "is",
      "display": "Icelandic"
    }, {
      "system": "https://fhir.hl7.org.uk/CodeSystem/UKCore-HumanLanguage",
      "code": "io",
      "display": "Ido"
    }, {
      "system": "https://fhir.hl7.org.uk/CodeSystem/UKCore-HumanLanguage",
      "code": "ig",
      "display": "Igbo"
    }, {
      "system": "https://fhir.hl7.org.uk/CodeSystem/UKCore-HumanLanguage",
      "code": "id",
      "display": "Indonesian"
    }, {
      "system": "https://fhir.hl7.org.uk/CodeSystem/UKCore-HumanLanguage",
      "code": "ia",
      "display": "Interlingua (International Auxiliary Language Association)"
    }, {
      "system": "https://fhir.hl7.org.uk/CodeSystem/UKCore-HumanLanguage",
      "code": "ie",
      "display": "Interlingue"
    }, {
      "system": "https://fhir.hl7.org.uk/CodeSystem/UKCore-HumanLanguage",
      "code": "iu",
      "display": "Inuktitut"
    }, {
      "system": "https://fhir.hl7.org.uk/CodeSystem/UKCore-HumanLanguage",
      "code": "ik",
      "display": "Inupiaq"
    }, {
      "system": "https://fhir.hl7.org.uk/CodeSystem/UKCore-HumanLanguage",
      "code": "ga",
      "display": "Irish"
    }, {
      "system": "https://fhir.hl7.org.uk/CodeSystem/UKCore-HumanLanguage",
      "code": "it",
      "display": "Italian"
    }, {
      "system": "https://fhir.hl7.org.uk/CodeSystem/UKCore-HumanLanguage",
      "code": "ja",
      "display": "Japanese"
    }, {
      "system": "https://fhir.hl7.org.uk/CodeSystem/UKCore-HumanLanguage",
      "code": "jv",
      "display": "Javanese"
    }, {
      "system": "https://fhir.hl7.org.uk/CodeSystem/UKCore-HumanLanguage",
      "code": "kl",
      "display": "Kalaallisut; Greenlandic"
    }, {
      "system": "https://fhir.hl7.org.uk/CodeSystem/UKCore-HumanLanguage",
      "code": "kn",
      "display": "Kannada"
    }, {
      "system": "https://fhir.hl7.org.uk/CodeSystem/UKCore-HumanLanguage",
      "code": "kr",
      "display": "Kanuri"
    }, {
      "system": "https://fhir.hl7.org.uk/CodeSystem/UKCore-HumanLanguage",
      "code": "ks",
      "display": "Kashmiri"
    }, {
      "system": "https://fhir.hl7.org.uk/CodeSystem/UKCore-HumanLanguage",
      "code": "kk",
      "display": "Kazakh"
    }, {
      "system": "https://fhir.hl7.org.uk/CodeSystem/UKCore-HumanLanguage",
      "code": "ki",
      "display": "Kikuyu; Gikuyu"
    }, {
      "system": "https://fhir.hl7.org.uk/CodeSystem/UKCore-HumanLanguage",
      "code": "rw",
      "display": "Kinyarwanda"
    }, {
      "system": "https://fhir.hl7.org.uk/CodeSystem/UKCore-HumanLanguage",
      "code": "ky",
      "display": "Kirghiz; Kyrgyz"
    }, {
      "system": "https://fhir.hl7.org.uk/CodeSystem/UKCore-HumanLanguage",
      "code": "kv",
      "display": "Komi"
    }, {
      "system": "https://fhir.hl7.org.uk/CodeSystem/UKCore-HumanLanguage",
      "code": "kg",
      "display": "Kongo"
    }, {
      "system": "https://fhir.hl7.org.uk/CodeSystem/UKCore-HumanLanguage",
      "code": "ko",
      "display": "Korean"
    }, {
      "system": "https://fhir.hl7.org.uk/CodeSystem/UKCore-HumanLanguage",
      "code": "kj",
      "display": "Kuanyama; Kwanyama"
    }, {
      "system": "https://fhir.hl7.org.uk/CodeSystem/UKCore-HumanLanguage",
      "code": "ku",
      "display": "Kurdish"
    }, {
      "system": "https://fhir.hl7.org.uk/CodeSystem/UKCore-HumanLanguage",
      "code": "lo",
      "display": "Lao"
    }, {
      "system": "https://fhir.hl7.org.uk/CodeSystem/UKCore-HumanLanguage",
      "code": "la",
      "display": "Latin"
    }, {
      "system": "https://fhir.hl7.org.uk/CodeSystem/UKCore-HumanLanguage",
      "code": "lv",
      "display": "Latvian"
    }, {
      "system": "https://fhir.hl7.org.uk/CodeSystem/UKCore-HumanLanguage",
      "code": "li",
      "display": "Limburgan; Limburger; Limburgish"
    }, {
      "system": "https://fhir.hl7.org.uk/CodeSystem/UKCore-HumanLanguage",
      "code": "ln",
      "display": "Lingala"
    }, {
      "system": "https://fhir.hl7.org.uk/CodeSystem/UKCore-HumanLanguage",
      "code": "lt",
      "display": "Lithuanian"
    }, {
      "system": "https://fhir.hl7.org.uk/CodeSystem/UKCore-HumanLanguage",
      "code": "lu",
      "display": "Luba-Katanga"
    }, {
      "system": "https://fhir.hl7.org.uk/CodeSystem/UKCore-HumanLanguage",
      "code": "lb",
      "display": "Luxembourgish; Letzeburgesch"
    }, {
      "system": "https://fhir.hl7.org.uk/CodeSystem/UKCore-HumanLanguage",
      "code": "mk",
      "display": "Macedonian"
    }, {
      "system": "https://fhir.hl7.org.uk/CodeSystem/UKCore-HumanLanguage",
      "code": "q5",
      "display": "Makaton"
    }, {
      "system": "https://fhir.hl7.org.uk/CodeSystem/UKCore-HumanLanguage",
      "code": "mg",
      "display": "Malagasy"
    }, {
      "system": "https://fhir.hl7.org.uk/CodeSystem/UKCore-HumanLanguage",
      "code": "ms",
      "display": "Malay"
    }, {
      "system": "https://fhir.hl7.org.uk/CodeSystem/UKCore-HumanLanguage",
      "code": "ml",
      "display": "Malayalam"
    }, {
      "system": "https://fhir.hl7.org.uk/CodeSystem/UKCore-HumanLanguage",
      "code": "mt",
      "display": "Maltese"
    }, {
      "system": "https://fhir.hl7.org.uk/CodeSystem/UKCore-HumanLanguage",
      "code": "gv",
      "display": "Manx"
    }, {
      "system": "https://fhir.hl7.org.uk/CodeSystem/UKCore-HumanLanguage",
      "code": "mi",
      "display": "Maori"
    }, {
      "system": "https://fhir.hl7.org.uk/CodeSystem/UKCore-HumanLanguage",
      "code": "mr",
      "display": "Marathi"
    }, {
      "system": "https://fhir.hl7.org.uk/CodeSystem/UKCore-HumanLanguage",
      "code": "mh",
      "display": "Marshallese"
    }, {
      "system": "https://fhir.hl7.org.uk/CodeSystem/UKCore-HumanLanguage",
      "code": "mo",
      "display": "Moldavian"
    }, {
      "system": "https://fhir.hl7.org.uk/CodeSystem/UKCore-HumanLanguage",
      "code": "mn",
      "display": "Mongolian"
    }, {
      "system": "https://fhir.hl7.org.uk/CodeSystem/UKCore-HumanLanguage",
      "code": "na",
      "display": "Nauru"
    }, {
      "system": "https://fhir.hl7.org.uk/CodeSystem/UKCore-HumanLanguage",
      "code": "nv",
      "display": "Navajo; Navaho"
    }, {
      "system": "https://fhir.hl7.org.uk/CodeSystem/UKCore-HumanLanguage",
      "code": "nd",
      "display": "Ndebele, North; North Ndebele"
    }, {
      "system": "https://fhir.hl7.org.uk/CodeSystem/UKCore-HumanLanguage",
      "code": "nr",
      "display": "Ndebele, South; South Ndebele"
    }, {
      "system": "https://fhir.hl7.org.uk/CodeSystem/UKCore-HumanLanguage",
      "code": "ng",
      "display": "Ndonga"
    }, {
      "system": "https://fhir.hl7.org.uk/CodeSystem/UKCore-HumanLanguage",
      "code": "ne",
      "display": "Nepali"
    }, {
      "system": "https://fhir.hl7.org.uk/CodeSystem/UKCore-HumanLanguage",
      "code": "se",
      "display": "Northern Sami"
    }, {
      "system": "https://fhir.hl7.org.uk/CodeSystem/UKCore-HumanLanguage",
      "code": "no",
      "display": "Norwegian"
    }, {
      "system": "https://fhir.hl7.org.uk/CodeSystem/UKCore-HumanLanguage",
      "code": "nn",
      "display": "Norwegian Nynorsk; Nynorsk, Norwegian"
    }, {
      "system": "https://fhir.hl7.org.uk/CodeSystem/UKCore-HumanLanguage",
      "code": "oc",
      "display": "Occitan (post1500); Provencal"
    }, {
      "system": "https://fhir.hl7.org.uk/CodeSystem/UKCore-HumanLanguage",
      "code": "oj",
      "display": "Ojibwa"
    }, {
      "system": "https://fhir.hl7.org.uk/CodeSystem/UKCore-HumanLanguage",
      "code": "or",
      "display": "Oriya"
    }, {
      "system": "https://fhir.hl7.org.uk/CodeSystem/UKCore-HumanLanguage",
      "code": "om",
      "display": "Oromo"
    }, {
      "system": "https://fhir.hl7.org.uk/CodeSystem/UKCore-HumanLanguage",
      "code": "os",
      "display": "Ossetian; Ossetic"
    }, {
      "system": "https://fhir.hl7.org.uk/CodeSystem/UKCore-HumanLanguage",
      "code": "pi",
      "display": "Pali"
    }, {
      "system": "https://fhir.hl7.org.uk/CodeSystem/UKCore-HumanLanguage",
      "code": "pa",
      "display": "Panjabi; Punjabi"
    }, {
      "system": "https://fhir.hl7.org.uk/CodeSystem/UKCore-HumanLanguage",
      "code": "fa",
      "display": "Persian"
    }, {
      "system": "https://fhir.hl7.org.uk/CodeSystem/UKCore-HumanLanguage",
      "code": "pl",
      "display": "Polish"
    }, {
      "system": "https://fhir.hl7.org.uk/CodeSystem/UKCore-HumanLanguage",
      "code": "pt",
      "display": "Portuguese"
    }, {
      "system": "https://fhir.hl7.org.uk/CodeSystem/UKCore-HumanLanguage",
      "code": "ps",
      "display": "Pushto"
    }, {
      "system": "https://fhir.hl7.org.uk/CodeSystem/UKCore-HumanLanguage",
      "code": "qu",
      "display": "Quechua"
    }, {
      "system": "https://fhir.hl7.org.uk/CodeSystem/UKCore-HumanLanguage",
      "code": "ro",
      "display": "Romanian"
    }, {
      "system": "https://fhir.hl7.org.uk/CodeSystem/UKCore-HumanLanguage",
      "code": "rm",
      "display": "Romansh"
    }, {
      "system": "https://fhir.hl7.org.uk/CodeSystem/UKCore-HumanLanguage",
      "code": "rn",
      "display": "Rundi"
    }, {
      "system": "https://fhir.hl7.org.uk/CodeSystem/UKCore-HumanLanguage",
      "code": "ru",
      "display": "Russian"
    }, {
      "system": "https://fhir.hl7.org.uk/CodeSystem/UKCore-HumanLanguage",
      "code": "sm",
      "display": "Samoan"
    }, {
      "system": "https://fhir.hl7.org.uk/CodeSystem/UKCore-HumanLanguage",
      "code": "sg",
      "display": "Sango"
    }, {
      "system": "https://fhir.hl7.org.uk/CodeSystem/UKCore-HumanLanguage",
      "code": "sa",
      "display": "Sanskrit"
    }, {
      "system": "https://fhir.hl7.org.uk/CodeSystem/UKCore-HumanLanguage",
      "code": "sc",
      "display": "Sardinian"
    }, {
      "system": "https://fhir.hl7.org.uk/CodeSystem/UKCore-HumanLanguage",
      "code": "sr",
      "display": "Serbian"
    }, {
      "system": "https://fhir.hl7.org.uk/CodeSystem/UKCore-HumanLanguage",
      "code": "sn",
      "display": "Shona"
    }, {
      "system": "https://fhir.hl7.org.uk/CodeSystem/UKCore-HumanLanguage",
      "code": "ii",
      "display": "Sichuan Yi"
    }, {
      "system": "https://fhir.hl7.org.uk/CodeSystem/UKCore-HumanLanguage",
      "code": "sd",
      "display": "Sindhi"
    }, {
      "system": "https://fhir.hl7.org.uk/CodeSystem/UKCore-HumanLanguage",
      "code": "si",
      "display": "Sinhala; Sinhalese"
    }, {
      "system": "https://fhir.hl7.org.uk/CodeSystem/UKCore-HumanLanguage",
      "code": "sk",
      "display": "Slovak"
    }, {
      "system": "https://fhir.hl7.org.uk/CodeSystem/UKCore-HumanLanguage",
      "code": "sl",
      "display": "Slovenian"
    }, {
      "system": "https://fhir.hl7.org.uk/CodeSystem/UKCore-HumanLanguage",
      "code": "so",
      "display": "Somali"
    }, {
      "system": "https://fhir.hl7.org.uk/CodeSystem/UKCore-HumanLanguage",
      "code": "st",
      "display": "Sotho, Southern"
    }, {
      "system": "https://fhir.hl7.org.uk/CodeSystem/UKCore-HumanLanguage",
      "code": "es",
      "display": "Spanish; Castilian"
    }, {
      "system": "https://fhir.hl7.org.uk/CodeSystem/UKCore-HumanLanguage",
      "code": "su",
      "display": "Sundanese"
    }, {
      "system": "https://fhir.hl7.org.uk/CodeSystem/UKCore-HumanLanguage",
      "code": "sw",
      "display": "Swahili"
    }, {
      "system": "https://fhir.hl7.org.uk/CodeSystem/UKCore-HumanLanguage",
      "code": "ss",
      "display": "Swati"
    }, {
      "system": "https://fhir.hl7.org.uk/CodeSystem/UKCore-HumanLanguage",
      "code": "sv",
      "display": "Swedish"
    }, {
      "system": "https://fhir.hl7.org.uk/CodeSystem/UKCore-HumanLanguage",
      "code": "tl",
      "display": "Tagalog"
    }, {
      "system": "https://fhir.hl7.org.uk/CodeSystem/UKCore-HumanLanguage",
      "code": "ty",
      "display": "Tahitian"
    }, {
      "system": "https://fhir.hl7.org.uk/CodeSystem/UKCore-HumanLanguage",
      "code": "tg",
      "display": "Tajik"
    }, {
      "system": "https://fhir.hl7.org.uk/CodeSystem/UKCore-HumanLanguage",
      "code": "ta",
      "display": "Tamil"
    }, {
      "system": "https://fhir.hl7.org.uk/CodeSystem/UKCore-HumanLanguage",
      "code": "tt",
      "display": "Tatar"
    }, {
      "system": "https://fhir.hl7.org.uk/CodeSystem/UKCore-HumanLanguage",
      "code": "te",
      "display": "Telugu"
    }, {
      "system": "https://fhir.hl7.org.uk/CodeSystem/UKCore-HumanLanguage",
      "code": "th",
      "display": "Thai"
    }, {
      "system": "https://fhir.hl7.org.uk/CodeSystem/UKCore-HumanLanguage",
      "code": "bo",
      "display": "Tibetan"
    }, {
      "system": "https://fhir.hl7.org.uk/CodeSystem/UKCore-HumanLanguage",
      "code": "ti",
      "display": "Tigrinya"
    }, {
      "system": "https://fhir.hl7.org.uk/CodeSystem/UKCore-HumanLanguage",
      "code": "to",
      "display": "Tonga (Tonga Islands)"
    }, {
      "system": "https://fhir.hl7.org.uk/CodeSystem/UKCore-HumanLanguage",
      "code": "ts",
      "display": "Tsonga"
    }, {
      "system": "https://fhir.hl7.org.uk/CodeSystem/UKCore-HumanLanguage",
      "code": "tn",
      "display": "Tswana"
    }, {
      "system": "https://fhir.hl7.org.uk/CodeSystem/UKCore-HumanLanguage",
      "code": "tr",
      "display": "Turkish"
    }, {
      "system": "https://fhir.hl7.org.uk/CodeSystem/UKCore-HumanLanguage",
      "code": "tk",
      "display": "Turkmen"
    }, {
      "system": "https://fhir.hl7.org.uk/CodeSystem/UKCore-HumanLanguage",
      "code": "tw",
      "display": "Twi"
    }, {
      "system": "https://fhir.hl7.org.uk/CodeSystem/UKCore-HumanLanguage",
      "code": "ug",
      "display": "Uighur; Uyghur"
    }, {
      "system": "https://fhir.hl7.org.uk/CodeSystem/UKCore-HumanLanguage",
      "code": "uk",
      "display": "Ukrainian"
    }, {
      "system": "https://fhir.hl7.org.uk/CodeSystem/UKCore-HumanLanguage",
      "code": "ur",
      "display": "Urdu"
    }, {
      "system": "https://fhir.hl7.org.uk/CodeSystem/UKCore-HumanLanguage",
      "code": "uz",
      "display": "Uzbek"
    }, {
      "system": "https://fhir.hl7.org.uk/CodeSystem/UKCore-HumanLanguage",
      "code": "ve",
      "display": "Venda"
    }, {
      "system": "https://fhir.hl7.org.uk/CodeSystem/UKCore-HumanLanguage",
      "code": "vi",
      "display": "Vietnamese"
    }, {
      "system": "https://fhir.hl7.org.uk/CodeSystem/UKCore-HumanLanguage",
      "code": "vo",
      "display": "Volapuk"
    }, {
      "system": "https://fhir.hl7.org.uk/CodeSystem/UKCore-HumanLanguage",
      "code": "wa",
      "display": "Walloon"
    }, {
      "system": "https://fhir.hl7.org.uk/CodeSystem/UKCore-HumanLanguage",
      "code": "cy",
      "display": "Welsh"
    }, {
      "system": "https://fhir.hl7.org.uk/CodeSystem/UKCore-HumanLanguage",
      "code": "fy",
      "display": "Western Frisian"
    }, {
      "system": "https://fhir.hl7.org.uk/CodeSystem/UKCore-HumanLanguage",
      "code": "wo",
      "display": "Wolof"
    }, {
      "system": "https://fhir.hl7.org.uk/CodeSystem/UKCore-HumanLanguage",
      "code": "xh",
      "display": "Xhosa"
    }, {
      "system": "https://fhir.hl7.org.uk/CodeSystem/UKCore-HumanLanguage",
      "code": "yi",
      "display": "Yiddish"
    }, {
      "system": "https://fhir.hl7.org.uk/CodeSystem/UKCore-HumanLanguage",
      "code": "yo",
      "display": "Yoruba"
    }, {
      "system": "https://fhir.hl7.org.uk/CodeSystem/UKCore-HumanLanguage",
      "code": "za",
      "display": "Zhuang; Chuang"
    }, {
      "system": "https://fhir.hl7.org.uk/CodeSystem/UKCore-HumanLanguage",
      "code": "zu",
      "display": "Zulu"
    } ]
  }
}